odoo8_addon_mgmtsystem_nonconformity_claim-8.0.1.0.0.99.dev11-nspkg.pth
odoo_addons/mgmtsystem_nonconformity_claim/README.rst
odoo_addons/mgmtsystem_nonconformity_claim/__init__.py
odoo_addons/mgmtsystem_nonconformity_claim/__openerp__.py
odoo_addons/mgmtsystem_nonconformity_claim/data/mgmtsystem_nonconformity_type.xml
odoo_addons/mgmtsystem_nonconformity_claim/i18n/de.po
odoo_addons/mgmtsystem_nonconformity_claim/i18n/es.po
odoo_addons/mgmtsystem_nonconformity_claim/i18n/fr.po
odoo_addons/mgmtsystem_nonconformity_claim/i18n/hr.po
odoo_addons/mgmtsystem_nonconformity_claim/i18n/id.po
odoo_addons/mgmtsystem_nonconformity_claim/i18n/mgmtsystem_nonconformity_claim.pot
odoo_addons/mgmtsystem_nonconformity_claim/i18n/nb.po
odoo_addons/mgmtsystem_nonconformity_claim/i18n/pt.po
odoo_addons/mgmtsystem_nonconformity_claim/i18n/pt_BR.po
odoo_addons/mgmtsystem_nonconformity_claim/i18n/sl.po
odoo_addons/mgmtsystem_nonconformity_claim/models/__init__.py
odoo_addons/mgmtsystem_nonconformity_claim/models/mgmtsystem_nonconformity.py
odoo_addons/mgmtsystem_nonconformity_claim/models/mgmtsystem_nonconformity_type.py
odoo_addons/mgmtsystem_nonconformity_claim/security/ir.model.access.csv
odoo_addons/mgmtsystem_nonconformity_claim/static/description/icon.png
odoo_addons/mgmtsystem_nonconformity_claim/views/mgmtsystem_nonconformity.xml
odoo_addons/mgmtsystem_nonconformity_claim/views/mgmtsystem_nonconformity_type.xml
odoo8_addon_mgmtsystem_nonconformity_claim-8.0.1.0.0.99.dev11.dist-info/METADATA
odoo8_addon_mgmtsystem_nonconformity_claim-8.0.1.0.0.99.dev11.dist-info/WHEEL
odoo8_addon_mgmtsystem_nonconformity_claim-8.0.1.0.0.99.dev11.dist-info/namespace_packages.txt
odoo8_addon_mgmtsystem_nonconformity_claim-8.0.1.0.0.99.dev11.dist-info/top_level.txt
odoo8_addon_mgmtsystem_nonconformity_claim-8.0.1.0.0.99.dev11.dist-info/RECORD
